env/__init__.py
env_cli-0.0.1.dist-info/LICENSE.txt
env_cli-0.0.1.dist-info/METADATA
env_cli-0.0.1.dist-info/WHEEL
env_cli-0.0.1.dist-info/entry_points.txt
env_cli-0.0.1.dist-info/top_level.txt
env_cli-0.0.1.dist-info/RECORD
