Metadata-Version: 2.1
Name: env-cli
Version: 0.0.1
Summary: UNKNOWN
Home-page: http://www.rt-thread.org/env-cli
Author: BernardXiong
Author-email: bernard.xiong@gmail.com
License: UNKNOWN
Keywords: RT-Thread IoT
Platform: UNKNOWN
Classifier: Development Status :: 3 - Alpha
Classifier: Intended Audience :: Developers
Classifier: Topic :: Software Development :: Build Tools
Classifier: License :: OSI Approved :: Apache Software License
Classifier: Programming Language :: Python
Requires-Python: >=2.7, !=3.0.*, !=3.1.*, !=3.2.*, !=3.3.*, <4
Requires-Dist: scons
Provides-Extra: dev
Requires-Dist: check-manifest ; extra == 'dev'
Provides-Extra: test
Requires-Dist: coverage ; extra == 'test'
